py_frontmatter/__init__.py
py_frontmatter/__main__.py
py_frontmatter/console/__init__.py
py_frontmatter/console/application.py
py_frontmatter/console/commands/__init__.py
py_frontmatter/console/commands/add_item.py
py_frontmatter/console/commands/add_tag.py
py_frontmatter/console/commands/base_command.py
py_frontmatter/console/commands/constants.py
py_frontmatter/console/commands/get.py
py_frontmatter/console/commands/remove_item.py
py_frontmatter/console/commands/remove_tag.py
py_frontmatter/console/commands/set.py
py_frontmatter/console/commands/utils.py
py_frontmatter/core/__init__.py
py_frontmatter/core/document.py
py_frontmatter/core/dump.py
py_frontmatter/core/load.py
py_frontmatter/py.typed
py_frontmatter-0.4.0.dist-info/entry_points.txt
py_frontmatter-0.4.0.dist-info/LICENSE
py_frontmatter-0.4.0.dist-info/WHEEL
py_frontmatter-0.4.0.dist-info/METADATA
py_frontmatter-0.4.0.dist-info/RECORD
