Metadata-Version: 2.1
Name: py-frontmatter
Version: 0.4.0
Summary: Manipulate YAML front matter.
License: Apache-2.0
Author: YEUNG King On
Author-email: koyeung@gmail.com
Requires-Python: >=3.10,<4.0
Classifier: License :: OSI Approved :: Apache Software License
Classifier: Programming Language :: Python :: 3
Classifier: Programming Language :: Python :: 3.10
Classifier: Programming Language :: Python :: 3.11
Requires-Dist: jsonpath-ng (>=1.5.3,<2.0.0)
Requires-Dist: ruamel.yaml (>=0.17.21,<0.18.0)
